wigner.cp311-win_amd64.pyd
wigner-2025.1.dist-info/licenses/LICENSE
wigner-2025.1.dist-info/METADATA
wigner-2025.1.dist-info/WHEEL
wigner-2025.1.dist-info/top_level.txt
wigner-2025.1.dist-info/RECORD
