Metadata-Version: 2.4
Name: wigner
Version: 2025.1
Summary: Wigner d functions, 3j symbols, 6j symbols
Author-email: Nicolas Tessore <n.tessore@ucl.ac.uk>
License: MIT License
Project-URL: Repository, https://github.com/ntessore/wigner
Classifier: Programming Language :: Python :: 3
Classifier: License :: OSI Approved :: MIT License
Classifier: Operating System :: OS Independent
Requires-Python: >=3.9
License-File: LICENSE
Requires-Dist: numpy<3,>=2.0
Dynamic: license-file
